{
 "status": 200,
 "date": "२०२५-१०-०९",
 "prices": [
  {
   "commodityname": "गोलभेडा ठूलो(भारतीय)",
   "commodityunit": "केजी",
   "minprice": "७०.००",
   "maxprice": "८०.००",
   "avgprice": "७५.००"
  },
  {
   "commodityname": "गोलभेडा सानो(लोकल)",
   "commodityunit": "के.जी.",
   "minprice": "१७.००",
   "maxprice": "२६.००",
   "avgprice": "२१.२०"
  },
  {
   "commodityname": "गोलभेडा सानो(टनेल)",
   "commodityunit": "के जी",
   "minprice": "२६.००",
   "maxprice": "४३.००",
   "avgprice": "३४.८०"
  },
  {
   "commodityname": "गोलभेडा सानो(भारतीय)",
   "commodityunit": "के जी",
   "minprice": "१८.००",
   "maxprice": "२५.००",
   "avgprice": "२२.८०"
  },
  {
   "commodityname": "आलु रातो",
   "commodityunit": "के.जी.",
   "minprice": "५२.००",
   "maxprice": "५४.००",
   "avgprice": "५२.६०"
  },
  {
   "commodityname": "आलु रातो(भारतीय)",
   "commodityunit": "के जी",
   "minprice": "३५.००",
   "maxprice": "३८.००",
   "avgprice": "३६.२०"
  },
  {
   "commodityname": "आलु रातो(मुडे)",
   "commodityunit": "केजी",
   "minprice": "४५.००",
   "maxprice": "४८.००",
   "avgprice": "४६.५०"
  },
  {
   "commodityname": "आलु सेतो",
   "commodityunit": "के.जी.",
   "minprice": "३७.००",
   "maxprice": "४०.००",
   "avgprice": "३९.००"
  },
  {
   "commodityname": "प्याज सुकेको (भारतीय)",
   "commodityunit": "के.जी.",
   "minprice": "३५.००",
   "maxprice": "३७.००",
   "avgprice": "३६.२०"
  },
  {
   "commodityname": "गाजर(लोकल)",
   "commodityunit": "के.जी.",
   "minprice": "१००.००",
   "maxprice": "११०.००",
   "avgprice": "१०३.००"
  },
  {
   "commodityname": "गाजर(तराई)",
   "commodityunit": "केजी",
   "minprice": "८५.००",
   "maxprice": "९५.००",
   "avgprice": "९०.००"
  },
  {
   "commodityname": "बन्दा(लोकल)",
   "commodityunit": "के.जी.",
   "minprice": "६०.००",
   "maxprice": "७०.००",
   "avgprice": "६५.००"
  },
  {
   "commodityname": "बन्दा(तराई)",
   "commodityunit": "केजी",
   "minprice": "४५.००",
   "maxprice": "५५.००",
   "avgprice": "५०.००"
  },
  {
   "commodityname": "काउली स्थानिय",
   "commodityunit": "के.जी.",
   "minprice": "५०.००",
   "maxprice": "६०.००",
   "avgprice": "५५.००"
  },
  {
   "commodityname": "काउली तराई",
   "commodityunit": "के.जी.",
   "minprice": "४०.००",
   "maxprice": "५०.००",
   "avgprice": "४५.००"
  },
  {
   "commodityname": "मूला रातो",
   "commodityunit": "के.जी.",
   "minprice": "५५.००",
   "maxprice": "६५.००",
   "avgprice": "५९.००"
  },
  {
   "commodityname": "मूला सेतो(लोकल)",
   "commodityunit": "के.जी.",
   "minprice": "४०.००",
   "maxprice": "४५.००",
   "avgprice": "४३.००"
  },
  {
   "commodityname": "सेतो मूला(हाइब्रीड)",
   "commodityunit": "केजी",
   "minprice": "४५.००",
   "maxprice": "५५.००",
   "avgprice": "४९.००"
  },
  {
   "commodityname": "भन्टा लाम्चो",
   "commodityunit": "के.जी.",
   "minprice": "२५.००",
   "maxprice": "३५.००",
   "avgprice": "२७.६०"
  },
  {
   "commodityname": "भन्टा डल्लो",
   "commodityunit": "के.जी.",
   "minprice": "३५.००",
   "maxprice": "४५.००",
   "avgprice": "४२.००"
  },
  {
   "commodityname": "बोडी(तने)",
   "commodityunit": "के.जी.",
   "minprice": "१००.००",
   "maxprice": "१२०.००",
   "avgprice": "११२.००"
  },
  {
   "commodityname": "मकै बोडी",
   "commodityunit": "केजी",
   "minprice": "६०.००",
   "maxprice": "७०.००",
   "avgprice": "६५.००"
  },
  {
   "commodityname": "मटरकोशा",
   "commodityunit": "के.जी.",
   "minprice": "२००.००",
   "maxprice": "२२०.००",
   "avgprice": "२१२.५०"
  },
  {
   "commodityname": "घिउ सिमी(लोकल)",
   "commodityunit": "के.जी.",
   "minprice": "१००.००",
   "maxprice": "१२०.००",
   "avgprice": "११०.००"
  },
  {
   "commodityname": "घिउ सिमी(हाइब्रीड)",
   "commodityunit": "केजी",
   "minprice": "९०.००",
   "maxprice": "१००.००",
   "avgprice": "९३.७५"
  },
  {
   "commodityname": "घिउ सिमी(राजमा)",
   "commodityunit": "केजी",
   "minprice": "२००.००",
   "maxprice": "२२०.००",
   "avgprice": "२१०.००"
  },
  {
   "commodityname": "टाटे सिमी",
   "commodityunit": "के.जी.",
   "minprice": "५०.००",
   "maxprice": "६०.००",
   "avgprice": "५५.००"
  },
  {
   "commodityname": "भटमासकोशा",
   "commodityunit": "के.जी.",
   "minprice": "७०.००",
   "maxprice": "८५.००",
   "avgprice": "७८.००"
  },
  {
   "commodityname": "तितो करेला",
   "commodityunit": "के.जी.",
   "minprice": "४०.००",
   "maxprice": "५०.००",
   "avgprice": "४४.५०"
  },
  {
   "commodityname": "लौका",
   "commodityunit": "के.जी.",
   "minprice": "५०.००",
   "maxprice": "६०.००",
   "avgprice": "५३.००"
  },
  {
   "commodityname": "परवर(लोकल)",
   "commodityunit": "के.जी.",
   "minprice": "६०.००",
   "maxprice": "७०.००",
   "avgprice": "६५.००"
  },
  {
   "commodityname": "परवर(तराई)",
   "commodityunit": "केजी",
   "minprice": "६०.००",
   "maxprice": "७०.००",
   "avgprice": "६५.००"
  },
  {
   "commodityname": "चिचिण्डो",
   "commodityunit": "के.जी.",
   "minprice": "३०.००",
   "maxprice": "४०.००",
   "avgprice": "३६.२५"
  },
  {
   "commodityname": "घिरौला",
   "commodityunit": "के.जी.",
   "minprice": "४०.००",
   "maxprice": "५०.००",
   "avgprice": "४६.६०"
  },
  {
   "commodityname": "फर्सी पाकेको",
   "commodityunit": "के.जी.",
   "minprice": "६०.००",
   "maxprice": "७०.००",
   "avgprice": "६५.००"
  },
  {
   "commodityname": "फर्सी हरियो(लाम्चो)",
   "commodityunit": "के.जी.",
   "minprice": "६०.००",
   "maxprice": "७०.००",
   "avgprice": "६५.००"
  },
  {
   "commodityname": "हरियो फर्सी(डल्लो)",
   "commodityunit": "केजी",
   "minprice": "३०.००",
   "maxprice": "४०.००",
   "avgprice": "३७.००"
  },
  {
   "commodityname": "सलगम",
   "commodityunit": "के.जी.",
   "minprice": "८०.००",
   "maxprice": "९०.००",
   "avgprice": "८५.००"
  },
  {
   "commodityname": "सखरखण्ड",
   "commodityunit": "के.जी.",
   "minprice": "७०.००",
   "maxprice": "८०.००",
   "avgprice": "७६.२५"
  },
  {
   "commodityname": "बरेला",
   "commodityunit": "के.जी.",
   "minprice": "१००.००",
   "maxprice": "१२०.००",
   "avgprice": "११०.००"
  },
  {
   "commodityname": "पिंडालू",
   "commodityunit": "के.जी.",
   "minprice": "७०.००",
   "maxprice": "८०.००",
   "avgprice": "७५.००"
  },
  {
   "commodityname": "स्कूस",
   "commodityunit": "के.जी.",
   "minprice": "१०.००",
   "maxprice": "१५.००",
   "avgprice": "१२.५०"
  },
  {
   "commodityname": "रायो साग",
   "commodityunit": "के.जी.",
   "minprice": "१००.००",
   "maxprice": "१२०.००",
   "avgprice": "११०.००"
  },
  {
   "commodityname": "पालूगो साग",
   "commodityunit": "के.जी.",
   "minprice": "९०.००",
   "maxprice": "११०.००",
   "avgprice": "१००.००"
  },
  {
   "commodityname": "चमसूरको साग",
   "commodityunit": "के.जी.",
   "minprice": "१३०.००",
   "maxprice": "१५०.००",
   "avgprice": "१४०.००"
  },
  {
   "commodityname": "तोरीको साग",
   "commodityunit": "के.जी.",
   "minprice": "७०.००",
   "maxprice": "८०.००",
   "avgprice": "७५.००"
  },
  {
   "commodityname": "प्याज हरियो",
   "commodityunit": "के.जी.",
   "minprice": "७०.००",
   "maxprice": "८०.००",
   "avgprice": "७५.००"
  },
  {
   "commodityname": "च्याउ(कन्य)",
   "commodityunit": "के.जी.",
   "minprice": "१७०.००",
   "maxprice": "१९०.००",
   "avgprice": "१८०.००"
  },
  {
   "commodityname": "च्याउ(डल्ले)",
   "commodityunit": "के जी",
   "minprice": "२५०.००",
   "maxprice": "३००.००",
   "avgprice": "२७०.००"
  },
  {
   "commodityname": "कुरीलो",
   "commodityunit": "के.जी.",
   "minprice": "३५०.००",
   "maxprice": "४५०.००",
   "avgprice": "४००.००"
  },
  {
   "commodityname": "न्यूरो",
   "commodityunit": "के.जी.",
   "minprice": "७०.००",
   "maxprice": "८०.००",
   "avgprice": "७५.००"
  },
  {
   "commodityname": "ब्रोकाउली",
   "commodityunit": "के.जी.",
   "minprice": "१५०.००",
   "maxprice": "१८०.००",
   "avgprice": "१६३.३३"
  },
  {
   "commodityname": "चुकुन्दर",
   "commodityunit": "के.जी.",
   "minprice": "६०.००",
   "maxprice": "७०.००",
   "avgprice": "६५.००"
  },
  {
   "commodityname": "रातो बन्दा",
   "commodityunit": "के.जी.",
   "minprice": "१६०.००",
   "maxprice": "१८०.००",
   "avgprice": "१७२.५०"
  },
  {
   "commodityname": "जिरीको साग",
   "commodityunit": "के.जी.",
   "minprice": "१५०.००",
   "maxprice": "१८०.००",
   "avgprice": "१५८.००"
  },
  {
   "commodityname": "सेलरी",
   "commodityunit": "के.जी.",
   "minprice": "२५०.००",
   "maxprice": "३००.००",
   "avgprice": "२७७.५०"
  },
  {
   "commodityname": "सौफको साग",
   "commodityunit": "के.जी.",
   "minprice": "१२०.००",
   "maxprice": "१४०.००",
   "avgprice": "१३०.००"
  },
  {
   "commodityname": "पुदीना",
   "commodityunit": "के.जी.",
   "minprice": "५००.००",
   "maxprice": "६००.००",
   "avgprice": "५७०.००"
  },
  {
   "commodityname": "गान्टे मूला",
   "commodityunit": "के.जी.",
   "minprice": "६०.००",
   "maxprice": "७०.००",
   "avgprice": "६५.००"
  },
  {
   "commodityname": "इमली",
   "commodityunit": "के.जी.",
   "minprice": "१७०.००",
   "maxprice": "१८०.००",
   "avgprice": "१७५.००"
  },
  {
   "commodityname": "तामा",
   "commodityunit": "के.जी.",
   "minprice": "१००.००",
   "maxprice": "१२०.००",
   "avgprice": "११०.००"
  },
  {
   "commodityname": "तोफु",
   "commodityunit": "के.जी.",
   "minprice": "१३०.००",
   "maxprice": "१४०.००",
   "avgprice": "१३५.००"
  },
  {
   "commodityname": "गुन्दुक",
   "commodityunit": "के.जी.",
   "minprice": "२५०.००",
   "maxprice": "३००.००",
   "avgprice": "२७५.००"
  },
  {
   "commodityname": "स्याउ(झोले)",
   "commodityunit": "के.जी.",
   "minprice": "२००.००",
   "maxprice": "२५०.००",
   "avgprice": "२२८.००"
  },
  {
   "commodityname": "स्याउ(फूजी)",
   "commodityunit": "के जी",
   "minprice": "२६०.००",
   "maxprice": "३००.००",
   "avgprice": "२८०.००"
  },
  {
   "commodityname": "केरा",
   "commodityunit": "दर्जन",
   "minprice": "१३५.००",
   "maxprice": "१४५.००",
   "avgprice": "१४०.००"
  },
  {
   "commodityname": "कागती",
   "commodityunit": "के.जी.",
   "minprice": "१३०.००",
   "maxprice": "१५०.००",
   "avgprice": "१४४.००"
  },
  {
   "commodityname": "अनार",
   "commodityunit": "के.जी.",
   "minprice": "३००.००",
   "maxprice": "३५०.००",
   "avgprice": "३२५.००"
  },
  {
   "commodityname": "सुन्तला(भारतीय)",
   "commodityunit": "केजी",
   "minprice": "१४०.००",
   "maxprice": "१५०.००",
   "avgprice": "१४६.००"
  },
  {
   "commodityname": "तरबुजा(हरियो)",
   "commodityunit": "के.जी.",
   "minprice": "६०.००",
   "maxprice": "७०.००",
   "avgprice": "६५.००"
  },
  {
   "commodityname": "मौसम",
   "commodityunit": "के.जी.",
   "minprice": "१६०.००",
   "maxprice": "१८०.००",
   "avgprice": "१७२.००"
  },
  {
   "commodityname": "जुनार",
   "commodityunit": "के.जी.",
   "minprice": "२४०.००",
   "maxprice": "२५०.००",
   "avgprice": "२४५.००"
  },
  {
   "commodityname": "भुई कटहर",
   "commodityunit": "प्रति गोटा",
   "minprice": "१५०.००",
   "maxprice": "१६०.००",
   "avgprice": "१५५.००"
  },
  {
   "commodityname": "काक्रो(लोकल)",
   "commodityunit": "के.जी.",
   "minprice": "७०.००",
   "maxprice": "८०.००",
   "avgprice": "७४.००"
  },
  {
   "commodityname": "काक्रो(हाइब्रीड)",
   "commodityunit": "के जी",
   "minprice": "३०.००",
   "maxprice": "४०.००",
   "avgprice": "३६.२५"
  },
  {
   "commodityname": "नासपाती(लोकल)",
   "commodityunit": "के.जी.",
   "minprice": "८०.००",
   "maxprice": "९०.००",
   "avgprice": "८५.००"
  },
  {
   "commodityname": "नासपाती(चाइनिज)",
   "commodityunit": "केजी",
   "minprice": "२००.००",
   "maxprice": "२४०.००",
   "avgprice": "२२२.५०"
  },
  {
   "commodityname": "मेवा(नेपाली)",
   "commodityunit": "के.जी.",
   "minprice": "४५.००",
   "maxprice": "५५.००",
   "avgprice": "५०.००"
  },
  {
   "commodityname": "मेवा(भारतीय)",
   "commodityunit": "केजी",
   "minprice": "९०.००",
   "maxprice": "१००.००",
   "avgprice": "९५.००"
  },
  {
   "commodityname": "अम्बा",
   "commodityunit": "के.जी.",
   "minprice": "८०.००",
   "maxprice": "१००.००",
   "avgprice": "९०.००"
  },
  {
   "commodityname": "लप्सी",
   "commodityunit": "के.जी.",
   "minprice": "५५.००",
   "maxprice": "६५.००",
   "avgprice": "६०.००"
  },
  {
   "commodityname": "किवि",
   "commodityunit": "केजी",
   "minprice": "२५०.००",
   "maxprice": "३००.००",
   "avgprice": "२७५.००"
  },
  {
   "commodityname": "शरीफा",
   "commodityunit": "के‍.जी",
   "minprice": "१००.००",
   "maxprice": "१२०.००",
   "avgprice": "११०.००"
  },
  {
   "commodityname": "आभोकाडो",
   "commodityunit": "के.जी",
   "minprice": "२५०.००",
   "maxprice": "३५०.००",
   "avgprice": "३००.००"
  },
  {
   "commodityname": "अमला",
   "commodityunit": "के.जी",
   "minprice": "७५.००",
   "maxprice": "८५.००",
   "avgprice": "८०.००"
  },
  {
   "commodityname": "अदुवा",
   "commodityunit": "के.जी.",
   "minprice": "१००.००",
   "maxprice": "१२०.००",
   "avgprice": "११०.००"
  },
  {
   "commodityname": "खु्र्सानी सुकेको",
   "commodityunit": "के.जी.",
   "minprice": "३५०.००",
   "maxprice": "४००.००",
   "avgprice": "३७५.००"
  },
  {
   "commodityname": "खु्र्सानी हरियो",
   "commodityunit": "के.जी.",
   "minprice": "५०.००",
   "maxprice": "६०.००",
   "avgprice": "५६.२५"
  },
  {
   "commodityname": "खुर्सानी हरियो(बुलेट)",
   "commodityunit": "के जी",
   "minprice": "५०.००",
   "maxprice": "६०.००",
   "avgprice": "५५.००"
  },
  {
   "commodityname": "खुर्सानी हरियो(माछे)",
   "commodityunit": "के जी",
   "minprice": "१००.००",
   "maxprice": "११०.००",
   "avgprice": "१०५.००"
  },
  {
   "commodityname": "खुर्सानी हरियो(अकबरे)",
   "commodityunit": "के जी",
   "minprice": "१००.००",
   "maxprice": "१५०.००",
   "avgprice": "१२५.००"
  },
  {
   "commodityname": "भेडे खु्र्सानी",
   "commodityunit": "के.जी.",
   "minprice": "१००.००",
   "maxprice": "१२०.००",
   "avgprice": "११०.००"
  },
  {
   "commodityname": "लसुन हरियो",
   "commodityunit": "के.जी.",
   "minprice": "२३०.००",
   "maxprice": "२६०.००",
   "avgprice": "२४८.००"
  },
  {
   "commodityname": "हरियो धनिया",
   "commodityunit": "के.जी.",
   "minprice": "८०.००",
   "maxprice": "११०.००",
   "avgprice": "९४.००"
  },
  {
   "commodityname": "लसुन सुकेको चाइनिज",
   "commodityunit": "के.जी.",
   "minprice": "२००.००",
   "maxprice": "२२०.००",
   "avgprice": "२१०.००"
  },
  {
   "commodityname": "लसुन सुकेको नेपाली",
   "commodityunit": "के.जी.",
   "minprice": "१४०.००",
   "maxprice": "१६०.००",
   "avgprice": "१५०.००"
  },
  {
   "commodityname": "छ्यापी सुकेको",
   "commodityunit": "के.जी.",
   "minprice": "१८०.००",
   "maxprice": "२००.००",
   "avgprice": "१९०.००"
  },
  {
   "commodityname": "छ्यापी हरियो",
   "commodityunit": "के.जी.",
   "minprice": "१८०.००",
   "maxprice": "२००.००",
   "avgprice": "१९०.००"
  },
  {
   "commodityname": "माछा सुकेको",
   "commodityunit": "के.जी.",
   "minprice": "८००.००",
   "maxprice": "१०००.००",
   "avgprice": "९००.००"
  },
  {
   "commodityname": "ताजा माछा(रहु)",
   "commodityunit": "के जी",
   "minprice": "३२०.००",
   "maxprice": "३४०.००",
   "avgprice": "३३०.००"
  },
  {
   "commodityname": "ताजा माछा(बचुवा)",
   "commodityunit": "के जी",
   "minprice": "२६०.००",
   "maxprice": "२८०.००",
   "avgprice": "२७०.००"
  },
  {
   "commodityname": "ताजा माछा(छडी)",
   "commodityunit": "के जी",
   "minprice": "२२०.००",
   "maxprice": "२३०.००",
   "avgprice": "२२५.००"
  },
  {
   "commodityname": "रुख टमाटर",
   "commodityunit": "केजी",
   "minprice": "१८०.००",
   "maxprice": "२००.००",
   "avgprice": "१९०.००"
  },
  {
   "commodityname": "राजा च्याउ",
   "commodityunit": "के.जी.",
   "minprice": "२८०.००",
   "maxprice": "३००.००",
   "avgprice": "२९०.००"
  },
  {
   "commodityname": "सिताके च्याउ",
   "commodityunit": "के.जी.",
   "minprice": "९००.००",
   "maxprice": "१०००.००",
   "avgprice": "९५०.००"
  }
 ]
}