{
 "status": 200,
 "date": "२०२४-०७-१५",
 "prices": [
  {
   "commodityname": "गोलभेडा ठूलो(नेपाली)",
   "commodityunit": "के.जी.",
   "minprice": "११०.००",
   "maxprice": "१३०.००",
   "avgprice": "१२०.००"
  },
  {
   "commodityname": "गोलभेडा सानो(लोकल)",
   "commodityunit": "के.जी.",
   "minprice": "४०.००",
   "maxprice": "४५.००",
   "avgprice": "४३.००"
  },
  {
   "commodityname": "गोलभेडा सानो(टनेल)",
   "commodityunit": "के जी",
   "minprice": "४५.००",
   "maxprice": "५५.००",
   "avgprice": "५०.००"
  },
  {
   "commodityname": "आलु रातो",
   "commodityunit": "के.जी.",
   "minprice": "६८.००",
   "maxprice": "७२.००",
   "avgprice": "७०.००"
  },
  {
   "commodityname": "आलु रातो(भारतीय)",
   "commodityunit": "के जी",
   "minprice": "५८.००",
   "maxprice": "६०.००",
   "avgprice": "५९.३३"
  },
  {
   "commodityname": "आलु रातो(मुडे)",
   "commodityunit": "केजी",
   "minprice": "५०.००",
   "maxprice": "५२.००",
   "avgprice": "५१.३३"
  },
  {
   "commodityname": "आलु सेतो",
   "commodityunit": "के.जी.",
   "minprice": "४८.००",
   "maxprice": "५०.००",
   "avgprice": "४९.००"
  },
  {
   "commodityname": "प्याज सुकेको (भारतीय)",
   "commodityunit": "के.जी.",
   "minprice": "९२.००",
   "maxprice": "९५.००",
   "avgprice": "९३.८०"
  },
  {
   "commodityname": "गाजर(लोकल)",
   "commodityunit": "के.जी.",
   "minprice": "९०.००",
   "maxprice": "१००.००",
   "avgprice": "९६.००"
  },
  {
   "commodityname": "बन्दा(लोकल)",
   "commodityunit": "के.जी.",
   "minprice": "५०.००",
   "maxprice": "६०.००",
   "avgprice": "५५.००"
  },
  {
   "commodityname": "काउली स्थानिय",
   "commodityunit": "के.जी.",
   "minprice": "५०.००",
   "maxprice": "६०.००",
   "avgprice": "५६.००"
  },
  {
   "commodityname": "स्थानीय काउली(ज्यापु)",
   "commodityunit": "केजी",
   "minprice": "७०.००",
   "maxprice": "८०.००",
   "avgprice": "७५.००"
  },
  {
   "commodityname": "मूला सेतो(लोकल)",
   "commodityunit": "के.जी.",
   "minprice": "२०.००",
   "maxprice": "३०.००",
   "avgprice": "२५.००"
  },
  {
   "commodityname": "सेतो मूला(हाइब्रीड)",
   "commodityunit": "केजी",
   "minprice": "२५.००",
   "maxprice": "३५.००",
   "avgprice": "३०.००"
  },
  {
   "commodityname": "भन्टा लाम्चो",
   "commodityunit": "के.जी.",
   "minprice": "८०.००",
   "maxprice": "९०.००",
   "avgprice": "८६.००"
  },
  {
   "commodityname": "भन्टा डल्लो",
   "commodityunit": "के.जी.",
   "minprice": "८०.००",
   "maxprice": "९०.००",
   "avgprice": "८६.६७"
  },
  {
   "commodityname": "बोडी(तने)",
   "commodityunit": "के.जी.",
   "minprice": "१००.००",
   "maxprice": "१२०.००",
   "avgprice": "११०.००"
  },
  {
   "commodityname": "मकै बोडी",
   "commodityunit": "केजी",
   "minprice": "९०.००",
   "maxprice": "१००.००",
   "avgprice": "९६.६७"
  },
  {
   "commodityname": "घिउ सिमी(लोकल)",
   "commodityunit": "के.जी.",
   "minprice": "१३०.००",
   "maxprice": "१६०.००",
   "avgprice": "१४६.००"
  },
  {
   "commodityname": "घिउ सिमी(हाइब्रीड)",
   "commodityunit": "केजी",
   "minprice": "१६०.००",
   "maxprice": "१८०.००",
   "avgprice": "१७०.००"
  },
  {
   "commodityname": "घिउ सिमी(राजमा)",
   "commodityunit": "केजी",
   "minprice": "१४०.००",
   "maxprice": "१५०.००",
   "avgprice": "१४६.६७"
  },
  {
   "commodityname": "भटमासकोशा",
   "commodityunit": "के.जी.",
   "minprice": "१३०.००",
   "maxprice": "१४०.००",
   "avgprice": "१३५.००"
  },
  {
   "commodityname": "तितो करेला",
   "commodityunit": "के.जी.",
   "minprice": "८०.००",
   "maxprice": "९०.००",
   "avgprice": "८६.००"
  },
  {
   "commodityname": "लौका",
   "commodityunit": "के.जी.",
   "minprice": "७०.००",
   "maxprice": "८०.००",
   "avgprice": "७६.६७"
  },
  {
   "commodityname": "परवर(लोकल)",
   "commodityunit": "के.जी.",
   "minprice": "७०.००",
   "maxprice": "८०.००",
   "avgprice": "७६.००"
  },
  {
   "commodityname": "चिचिण्डो",
   "commodityunit": "के.जी.",
   "minprice": "६०.००",
   "maxprice": "७०.००",
   "avgprice": "६६.६७"
  },
  {
   "commodityname": "घिरौला",
   "commodityunit": "के.जी.",
   "minprice": "९०.००",
   "maxprice": "१००.००",
   "avgprice": "९६.००"
  },
  {
   "commodityname": "झिगूनी",
   "commodityunit": "के.जी.",
   "minprice": "६०.००",
   "maxprice": "७०.००",
   "avgprice": "६६.६७"
  },
  {
   "commodityname": "फर्सी पाकेको",
   "commodityunit": "के.जी.",
   "minprice": "५०.००",
   "maxprice": "५५.००",
   "avgprice": "५१.६७"
  },
  {
   "commodityname": "हरियो फर्सी(डल्लो)",
   "commodityunit": "केजी",
   "minprice": "८०.००",
   "maxprice": "९०.००",
   "avgprice": "८६.००"
  },
  {
   "commodityname": "भिण्डी",
   "commodityunit": "के.जी.",
   "minprice": "१३०.००",
   "maxprice": "१५०.००",
   "avgprice": "१३८.००"
  },
  {
   "commodityname": "स्कूस",
   "commodityunit": "के.जी.",
   "minprice": "७०.००",
   "maxprice": "८०.००",
   "avgprice": "७६.००"
  },
  {
   "commodityname": "रायो साग",
   "commodityunit": "के.जी.",
   "minprice": "२००.००",
   "maxprice": "२५०.००",
   "avgprice": "२३३.३३"
  },
  {
   "commodityname": "प्याज हरियो",
   "commodityunit": "के.जी.",
   "minprice": "१४०.००",
   "maxprice": "१५०.००",
   "avgprice": "१४६.६७"
  },
  {
   "commodityname": "च्याउ(कन्य)",
   "commodityunit": "के.जी.",
   "minprice": "२००.००",
   "maxprice": "२५०.००",
   "avgprice": "२१८.००"
  },
  {
   "commodityname": "च्याउ(डल्ले)",
   "commodityunit": "के जी",
   "minprice": "४००.००",
   "maxprice": "४६०.००",
   "avgprice": "४३२.००"
  },
  {
   "commodityname": "कुरीलो",
   "commodityunit": "के.जी.",
   "minprice": "२५०.००",
   "maxprice": "३००.००",
   "avgprice": "२७५.००"
  },
  {
   "commodityname": "न्यूरो",
   "commodityunit": "के.जी.",
   "minprice": "१२०.००",
   "maxprice": "१४०.००",
   "avgprice": "१३०.००"
  },
  {
   "commodityname": "ब्रोकाउली",
   "commodityunit": "के.जी.",
   "minprice": "१४०.००",
   "maxprice": "१६०.००",
   "avgprice": "१५०.००"
  },
  {
   "commodityname": "चुकुन्दर",
   "commodityunit": "के.जी.",
   "minprice": "६०.००",
   "maxprice": "७०.००",
   "avgprice": "६६.६७"
  },
  {
   "commodityname": "सजिवन",
   "commodityunit": "के.जी.",
   "minprice": "५००.००",
   "maxprice": "५२०.००",
   "avgprice": "५१०.००"
  },
  {
   "commodityname": "रातो बन्दा",
   "commodityunit": "के.जी.",
   "minprice": "६०.००",
   "maxprice": "७०.००",
   "avgprice": "६५.००"
  },
  {
   "commodityname": "जिरीको साग",
   "commodityunit": "के.जी.",
   "minprice": "४००.००",
   "maxprice": "५००.००",
   "avgprice": "४५०.००"
  },
  {
   "commodityname": "सेलरी",
   "commodityunit": "के.जी.",
   "minprice": "२००.००",
   "maxprice": "२२०.००",
   "avgprice": "२१०.००"
  },
  {
   "commodityname": "पार्सले",
   "commodityunit": "के.जी.",
   "minprice": "५००.००",
   "maxprice": "५५०.००",
   "avgprice": "५२५.००"
  },
  {
   "commodityname": "पुदीना",
   "commodityunit": "के.जी.",
   "minprice": "५००.००",
   "maxprice": "५५०.००",
   "avgprice": "५२५.००"
  },
  {
   "commodityname": "गान्टे मूला",
   "commodityunit": "के.जी.",
   "minprice": "८०.००",
   "maxprice": "९०.००",
   "avgprice": "८६.६७"
  },
  {
   "commodityname": "इमली",
   "commodityunit": "के.जी.",
   "minprice": "१५०.००",
   "maxprice": "१६०.००",
   "avgprice": "१५६.६७"
  },
  {
   "commodityname": "तामा",
   "commodityunit": "के.जी.",
   "minprice": "१००.००",
   "maxprice": "१२०.००",
   "avgprice": "११३.३३"
  },
  {
   "commodityname": "तोफु",
   "commodityunit": "के.जी.",
   "minprice": "१५०.००",
   "maxprice": "१६०.००",
   "avgprice": "१५६.६७"
  },
  {
   "commodityname": "गुन्दुक",
   "commodityunit": "के.जी.",
   "minprice": "२५०.००",
   "maxprice": "३००.००",
   "avgprice": "२७५.००"
  },
  {
   "commodityname": "स्याउ(फूजी)",
   "commodityunit": "के जी",
   "minprice": "३००.००",
   "maxprice": "३२०.००",
   "avgprice": "३१३.३३"
  },
  {
   "commodityname": "केरा",
   "commodityunit": "दर्जन",
   "minprice": "१३०.००",
   "maxprice": "१४०.००",
   "avgprice": "१३६.६७"
  },
  {
   "commodityname": "कागती",
   "commodityunit": "के.जी.",
   "minprice": "२५०.००",
   "maxprice": "२८०.००",
   "avgprice": "२६४.००"
  },
  {
   "commodityname": "अनार",
   "commodityunit": "के.जी.",
   "minprice": "३५०.००",
   "maxprice": "४००.००",
   "avgprice": "३७५.००"
  },
  {
   "commodityname": "आँप(मालदह)",
   "commodityunit": "के.जी.",
   "minprice": "१२०.००",
   "maxprice": "१३०.००",
   "avgprice": "१२६.६७"
  },
  {
   "commodityname": "आँप(दसहरी)",
   "commodityunit": "केजी",
   "minprice": "१२०.००",
   "maxprice": "१३०.००",
   "avgprice": "१२६.६७"
  },
  {
   "commodityname": "तरबुजा(हरियो)",
   "commodityunit": "के.जी.",
   "minprice": "६५.००",
   "maxprice": "७०.००",
   "avgprice": "६८.३३"
  },
  {
   "commodityname": "मौसम",
   "commodityunit": "के.जी.",
   "minprice": "१६०.००",
   "maxprice": "१८०.००",
   "avgprice": "१७०.००"
  },
  {
   "commodityname": "जुनार",
   "commodityunit": "के.जी.",
   "minprice": "२४०.००",
   "maxprice": "२५०.००",
   "avgprice": "२४५.००"
  },
  {
   "commodityname": "भुई कटहर",
   "commodityunit": "प्रति गोटा",
   "minprice": "१६०.००",
   "maxprice": "१८०.००",
   "avgprice": "१७०.००"
  },
  {
   "commodityname": "काक्रो(लोकल)",
   "commodityunit": "के.जी.",
   "minprice": "९०.००",
   "maxprice": "१००.००",
   "avgprice": "९६.००"
  },
  {
   "commodityname": "काक्रो(हाइब्रीड)",
   "commodityunit": "के जी",
   "minprice": "६०.००",
   "maxprice": "८०.००",
   "avgprice": "७२.००"
  },
  {
   "commodityname": "रुख कटहर",
   "commodityunit": "के.जी.",
   "minprice": "४०.००",
   "maxprice": "५०.००",
   "avgprice": "४३.३३"
  },
  {
   "commodityname": "नासपाती(लोकल)",
   "commodityunit": "के.जी.",
   "minprice": "८०.००",
   "maxprice": "१००.००",
   "avgprice": "९०.००"
  },
  {
   "commodityname": "नासपाती(चाइनिज)",
   "commodityunit": "केजी",
   "minprice": "२२०.००",
   "maxprice": "२५०.००",
   "avgprice": "२३५.००"
  },
  {
   "commodityname": "मेवा(भारतीय)",
   "commodityunit": "केजी",
   "minprice": "९०.००",
   "maxprice": "१००.००",
   "avgprice": "९६.६७"
  },
  {
   "commodityname": "किवि",
   "commodityunit": "केजी",
   "minprice": "४५०.००",
   "maxprice": "५००.००",
   "avgprice": "४७५.००"
  },
  {
   "commodityname": "आभोकाडो",
   "commodityunit": "के.जी",
   "minprice": "५५०.००",
   "maxprice": "६००.००",
   "avgprice": "५७५.००"
  },
  {
   "commodityname": "अदुवा",
   "commodityunit": "के.जी.",
   "minprice": "२००.००",
   "maxprice": "२२०.००",
   "avgprice": "२१२.००"
  },
  {
   "commodityname": "खु्र्सानी सुकेको",
   "commodityunit": "के.जी.",
   "minprice": "४६०.००",
   "maxprice": "५००.००",
   "avgprice": "४८०.००"
  },
  {
   "commodityname": "खु्र्सानी हरियो",
   "commodityunit": "के.जी.",
   "minprice": "९०.००",
   "maxprice": "१००.००",
   "avgprice": "९६.००"
  },
  {
   "commodityname": "खुर्सानी हरियो(बुलेट)",
   "commodityunit": "के जी",
   "minprice": "९०.००",
   "maxprice": "१००.००",
   "avgprice": "९६.००"
  },
  {
   "commodityname": "खुर्सानी हरियो(माछे)",
   "commodityunit": "के जी",
   "minprice": "८०.००",
   "maxprice": "१००.००",
   "avgprice": "९०.००"
  },
  {
   "commodityname": "खुर्सानी हरियो(अकबरे)",
   "commodityunit": "के जी",
   "minprice": "३५०.००",
   "maxprice": "४५०.००",
   "avgprice": "४००.००"
  },
  {
   "commodityname": "भेडे खु्र्सानी",
   "commodityunit": "के.जी.",
   "minprice": "१००.००",
   "maxprice": "१२०.००",
   "avgprice": "११०.००"
  },
  {
   "commodityname": "लसुन हरियो",
   "commodityunit": "के.जी.",
   "minprice": "१४०.००",
   "maxprice": "१५०.००",
   "avgprice": "१४६.६७"
  },
  {
   "commodityname": "हरियो धनिया",
   "commodityunit": "के.जी.",
   "minprice": "२५०.००",
   "maxprice": "३५०.००",
   "avgprice": "३१२.५०"
  },
  {
   "commodityname": "लसुन सुकेको चाइनिज",
   "commodityunit": "के.जी.",
   "minprice": "२३०.००",
   "maxprice": "२५०.००",
   "avgprice": "२४०.००"
  },
  {
   "commodityname": "लसुन सुकेको नेपाली",
   "commodityunit": "के.जी.",
   "minprice": "१८०.००",
   "maxprice": "२००.००",
   "avgprice": "१९३.३३"
  },
  {
   "commodityname": "छ्यापी सुकेको",
   "commodityunit": "के.जी.",
   "minprice": "१५०.००",
   "maxprice": "१६०.००",
   "avgprice": "१५५.००"
  },
  {
   "commodityname": "ताजा माछा(रहु)",
   "commodityunit": "के जी",
   "minprice": "३४०.००",
   "maxprice": "३५०.००",
   "avgprice": "३४५.००"
  },
  {
   "commodityname": "ताजा माछा(बचुवा)",
   "commodityunit": "के जी",
   "minprice": "२५०.००",
   "maxprice": "२६०.००",
   "avgprice": "२५५.००"
  },
  {
   "commodityname": "ताजा माछा(छडी)",
   "commodityunit": "के जी",
   "minprice": "२४०.००",
   "maxprice": "२५०.००",
   "avgprice": "२४६.६७"
  },
  {
   "commodityname": "राजा च्याउ",
   "commodityunit": "के.जी.",
   "minprice": "२८०.००",
   "maxprice": "३००.००",
   "avgprice": "२९०.००"
  }
 ]
}